LICENSE.txt
MANIFEST.in
README.md
setup.cfg
setup.py
dhlparcel/__init__.py
dhlparcel/api.py
dhlparcel/auth_handler.py
dhlparcel/cache_handler.py
dhlparcel/config.py
dhlparcel/cache/__init__.py
dhlparcel/endpoints/__init__.py
dhlparcel/endpoints/base.py
dhlparcel/endpoints/capabilities.py
dhlparcel/endpoints/labels.py
dhlparcel/endpoints/parcel_types.py
dhlparcel/endpoints/parcelshops.py
dhlparcel/endpoints/pickup_availability.py
dhlparcel/endpoints/products.py
dhlparcel/endpoints/shipments.py
dhlparcel/models/__init__.py
dhlparcel/models/base.py
dhlparcel/models/errors.py
python_dhlparcel_api.egg-info/PKG-INFO
python_dhlparcel_api.egg-info/SOURCES.txt
python_dhlparcel_api.egg-info/dependency_links.txt
python_dhlparcel_api.egg-info/requires.txt
python_dhlparcel_api.egg-info/top_level.txt