Metadata-Version: 2.1
Name: python-dhlparcel-api
Version: 0.0.2
Summary: Wrapper for the DHL Parcel API endpoints
Home-page: https://github.com/alexander-schillemans/python-dhlparcel-api
Author: Alexander Schillemans
Author-email: alexander.schillemans@hotmail.com
License: GPL-3.0-or-later
Download-URL: https://github.com/alexander-schillemans/python-dhlparcel-api/archive/refs/tags/0.0.2.tar.gz
Keywords: dhl,dhl parcel
Platform: UNKNOWN
Classifier: Development Status :: 3 - Alpha
Classifier: Intended Audience :: Developers
Classifier: Topic :: Software Development :: Build Tools
Classifier: License :: OSI Approved :: GNU General Public License v3 or later (GPLv3+)
Classifier: Programming Language :: Python :: 3
License-File: LICENSE.txt
